gitlab_ci_verify_bin-2.8.3.dist-info/METADATA
gitlab_ci_verify_bin-2.8.3.dist-info/WHEEL
gitlab_ci_verify_bin-2.8.3.dist-info/entry_points.txt
gitlab_ci_verify_bin/__init__.py
gitlab_ci_verify_bin/__main__.py
gitlab_ci_verify_bin/exec.py
gitlab_ci_verify_bin/gitlab-ci-verify
gitlab_ci_verify_bin-2.8.3.dist-info/RECORD
