Metadata-Version: 2.1
Name: gitlab-ci-verify-bin
Version: 2.8.3
Summary: Validate and lint your gitlab ci files using ShellCheck, the Gitlab
License: GPL-3.0
Classifier: License :: OSI Approved :: GNU General Public License v3 (GPLv3)
Classifier: Development Status :: 4 - Beta
Classifier: Intended Audience :: Developers
Classifier: Environment :: Console
Classifier: Environment :: MacOS X
Classifier: Operating System :: POSIX
Classifier: Operating System :: Unix
Classifier: Environment :: Win32 (MS Windows)
Classifier: Programming Language :: Python :: 3
Classifier: Programming Language :: Python :: 3.8
Classifier: Programming Language :: Python :: 3.9
Classifier: Programming Language :: Python :: 3.10
Classifier: Programming Language :: Python :: 3.11
Classifier: Programming Language :: Python :: 3.12
Project-URL: Homepage, https://github.com/timo-reymann/gitlab-ci-verify
Project-URL: Source Code, https://github.com/timo-reymann/gitlab-ci-verify.git
Project-URL:
Requires-Python: >=3.8
